ProtopiaAgent/__init__.py
ProtopiaAgent/agent.py
agent/__init__.py
agent/agent.py
protopia/__init__.py
protopia/agent.py
protopia/api/__init__.py
protopia/api/data/__init__.py
protopia/api/data/v1beta1/__init__.py
protopia/api/data/v1beta1/data_source_pb2.py
protopia/api/data/v1beta1/data_source_pb2_grpc.py
protopia/api/iam/__init__.py
protopia/api/iam/v1beta1/__init__.py
protopia/api/iam/v1beta1/iam_policy_pb2.py
protopia/api/iam/v1beta1/iam_policy_pb2_grpc.py
protopia/api/iam/v1beta1/iam_role_pb2.py
protopia/api/iam/v1beta1/iam_role_pb2_grpc.py
protopia/api/iam/v1beta1/policy_pb2.py
protopia/api/iam/v1beta1/policy_pb2_grpc.py
protopia/api/iam/v1beta1/role_pb2.py
protopia/api/iam/v1beta1/role_pb2_grpc.py
protopia/api/naming/__init__.py
protopia/api/naming/v1beta1/__init__.py
protopia/api/naming/v1beta1/prn_pb2.py
protopia/api/naming/v1beta1/prn_pb2_grpc.py
protopia/api/noise/__init__.py
protopia/api/noise/v1beta1/__init__.py
protopia/api/noise/v1beta1/distribution_pb2.py
protopia/api/noise/v1beta1/distribution_pb2_grpc.py
protopia/api/noise/v1beta1/internal/__init__.py
protopia/api/noise/v1beta1/internal/store_pb2.py
protopia/api/noise/v1beta1/internal/store_pb2_grpc.py
protopia/api/tenant/__init__.py
protopia/api/tenant/v1beta1/__init__.py
protopia/api/tenant/v1beta1/organization_pb2.py
protopia/api/tenant/v1beta1/organization_pb2_grpc.py
protopia/grpc_auth/__init__.py
protopia/grpc_auth/jwt.py
protopia/noise_layer/__init__.py
protopia/noise_layer/cloak.py
protopia-agent/__init__.py
protopia-agent/agent.py
protopia-0.3.2.dist-info/METADATA
protopia-0.3.2.dist-info/WHEEL
protopia-0.3.2.dist-info/top_level.txt
protopia-0.3.2.dist-info/RECORD
