Metadata-Version: 2.1
Name: protopia
Version: 0.3.2
Summary: Python agent for protopia
Home-page: https://github.com/protopia-ai/py-agent
Author: Alan Synn
Author-email: alan@protopia.ai
License: UNKNOWN
Download-URL: https://github.com/protopia-ai/py-agent/archive/0.2.1.tar.gz
Keywords: protopia,protopia-agent
Platform: UNKNOWN
Classifier: Programming Language :: Python :: 3
Classifier: Programming Language :: Python :: 3.5
Classifier: Programming Language :: Python :: 3.6
Classifier: Programming Language :: Python :: 3.7
Classifier: Programming Language :: Python :: 3.8
Classifier: Programming Language :: Python :: 3.9
Requires-Python: >=3
Requires-Dist: grpcio (>=1.34.1)
Requires-Dist: grpcio-tools (>=1.34.1)
Requires-Dist: oauthlib (>=3.1.0)
Requires-Dist: requests-oauthlib (>=1.3.0)
Requires-Dist: torch (>=1.0.0)
